irctk_bot/__init__.py
irctk_bot/__main__.py
irctk_bot/argument_parser.py
irctk_bot/cli.py
irctk_bot/command.py
irctk_bot/context.py
irctk_bot/controller.py
irctk_bot/module.py
irctk_bot/modules/__init__.py
irctk_bot/modules/help.py
irctk_bot/modules/ping.py
irctk_bot-0.2.2.dist-info/METADATA
irctk_bot-0.2.2.dist-info/WHEEL
irctk_bot-0.2.2.dist-info/entry_points.txt
irctk_bot-0.2.2.dist-info/RECORD
