Metadata-Version: 2.1
Name: irctk-bot
Version: 0.2.2
Summary: Bot framework for irctk
License: BSD
Author: Kyle Fuller
Author-email: kyle@fuller.li
Requires-Python: >=3.11,<4.0
Classifier: License :: Other/Proprietary License
Classifier: Programming Language :: Python :: 3
Classifier: Programming Language :: Python :: 3.11
Classifier: Programming Language :: Python :: 3.12
Classifier: Programming Language :: Python :: 3.13
Requires-Dist: irc-toolkit (>=0.4.0,<0.5.0)
